isypy/__init__.py
isypy/__main__.py
isypy/abc_markovchain.py
isypy/ising.py
isypy/isypy.py
isypy/monte_carlo.py
isypy/timerpy.py
isypy/tools.py
isypy/tests/__init__.py
isypy/tests/test_ising.py
isypy/tests/test_monte_carlo.py
isypy/tests/test_timerpy.py
isypy-1.0.0.dist-info/LICENSE
isypy-1.0.0.dist-info/METADATA
isypy-1.0.0.dist-info/WHEEL
isypy-1.0.0.dist-info/top_level.txt
isypy-1.0.0.dist-info/RECORD
