Metadata-Version: 2.1
Name: isypy
Version: 1.0.0
Summary: Simple Ising solver.
Home-page: UNKNOWN
Author: Charles-David Hevert
Author-email: charles-david.hebert@usherbrooke.ca
License: MIT
Keywords: Physics
Platform: UNKNOWN
Classifier: Development Status :: 3 - Alpha
Classifier: Intended Audience :: Developers
Classifier: Topic :: Software Development :: Build Tools
Classifier: License :: OSI Approved :: MIT License
Classifier: Programming Language :: Python :: 3.6
Requires-Dist: numpy
Requires-Dist: scipy
Requires-Dist: pyyaml
